{
  "name": "clojure",
  "rules": {
    "program": {
      "type": "REPEAT",
      "content": {
        "type": "SYMBOL",
        "name": "_expression"
      }
    },
    "_expression": {
      "type": "CHOICE",
      "members": [
        {
          "type": "SYMBOL",
          "name": "nil"
        },
        {
          "type": "SYMBOL",
          "name": "true"
        },
        {
          "type": "SYMBOL",
          "name": "false"
        }
      ]
    },
    "true": {
      "type": "STRING",
      "value": "true"
    },
    "false": {
      "type": "STRING",
      "value": "false"
    },
    "nil": {
      "type": "STRING",
      "value": "nil"
    }
  },
  "extras": [
    {
      "type": "PATTERN",
      "value": "\\s"
    }
  ],
  "conflicts": [],
  "externals": [],
  "inline": []
}